Metadata-Version: 2.1
Name: hubsale
Version: 0.0.3
Summary: Hubsale Api python connection
Home-page: https://github.com/Fr4ncisTaylor/HubSale-api
Author: Francis Taylor
Author-email: Francistrapp2000@gmail.com
License: Apache License
Keywords: hubsale
Platform: UNKNOWN
